agentbill_langchain/__init__.py
agentbill_langchain/callback.py
agentbill_pcu_tools_2025-1.0.3.dist-info/licenses/LICENSE
agentbill_pcu_tools_2025-1.0.3.dist-info/METADATA
agentbill_pcu_tools_2025-1.0.3.dist-info/WHEEL
agentbill_pcu_tools_2025-1.0.3.dist-info/top_level.txt
agentbill_pcu_tools_2025-1.0.3.dist-info/RECORD
