Metadata-Version: 2.4
Name: agentbill-pcu-tools-2025
Version: 1.0.3
Summary: LangChain callback handler for automatic usage tracking and billing with AgentBill
Home-page: https://github.com/Agent-Bill/langchain
Author: AgentBill
Author-email: support@agentbill.com
Keywords: langchain agentbill ai agent billing usage-tracking openai anthropic llm observability callbacks
Classifier: Development Status :: 4 - Beta
Classifier: Intended Audience :: Developers
Classifier: Topic :: Software Development :: Libraries :: Python Modules
Classifier: License :: OSI Approved :: MIT License
Classifier: Programming Language :: Python :: 3
Classifier: Programming Language :: Python :: 3.8
Classifier: Programming Language :: Python :: 3.9
Classifier: Programming Language :: Python :: 3.10
Classifier: Programming Language :: Python :: 3.11
Classifier: Programming Language :: Python :: 3.12
Requires-Python: >=3.8
License-File: LICENSE
Requires-Dist: langchain>=0.1.0
Requires-Dist: requests>=2.28.0
Provides-Extra: openai
Requires-Dist: langchain-openai>=0.0.1; extra == "openai"
Provides-Extra: anthropic
Requires-Dist: langchain-anthropic>=0.0.1; extra == "anthropic"
Dynamic: author
Dynamic: author-email
Dynamic: classifier
Dynamic: description
Dynamic: description-content-type
Dynamic: home-page
Dynamic: keywords
Dynamic: license-file
Dynamic: provides-extra
Dynamic: requires-dist
Dynamic: requires-python
Dynamic: summary
